aws_empty_bucket/__init__.py
aws_empty_bucket/empty_s3_bucket.py
aws_empty_bucket/package/__init__.py
aws_empty_bucket/package/action.py
aws_empty_bucket/package/cfnresponse.py
aws_empty_bucket/package/index.py
aws_empty_bucket-2.4.0.dist-info/LICENSE
aws_empty_bucket-2.4.0.dist-info/METADATA
aws_empty_bucket-2.4.0.dist-info/WHEEL
aws_empty_bucket-2.4.0.dist-info/top_level.txt
aws_empty_bucket-2.4.0.dist-info/RECORD
