Metadata-Version: 2.1
Name: aws-empty-bucket
Version: 2.4.0
Summary: AWS CDK package that empties an S3 bucket upon resource deletion.
Home-page: https://github.com/idenfy/AwsEmptyBucket.git
Author: Laimonas Sutkus
Author-email: laimonas@idenfy.com, laimonas.sutkus@gmail.com
License: GNU GENERAL PUBLIC LICENSE Version 3
Keywords: AWS CDK S3 CustomResource
Platform: UNKNOWN
Classifier: Programming Language :: Python :: 3.6
Classifier: Programming Language :: Python :: 3.7
Classifier: Programming Language :: Python :: 3.8
Classifier: Operating System :: OS Independent
Requires-Dist: aws-cdk.core (<2.0.0,>=1.60.0)
Requires-Dist: aws-cdk.aws-iam (<2.0.0,>=1.60.0)
Requires-Dist: aws-cdk.custom-resources (<2.0.0,>=1.60.0)
Requires-Dist: aws-cdk.aws-s3 (<2.0.0,>=1.60.0)
Requires-Dist: aws-cdk.aws-s3-deployment (<2.0.0,>=1.60.0)
